{
    "rating": "PG-13", 
    "studios": [
        "Zexcs"
    ], 
    "licensors": [
        "Funimation"
    ], 
    "title": "Shounen Hollywood: Holly Stage for 50", 
    "url": "/anime/27741/Shounen_Hollywood__Holly_Stage_for_50", 
    "popularity": 5158, 
    "public_score": 6.64, 
    "genres": [
        "Music", 
        "Slice of Life", 
        "Shoujo"
    ], 
    "rank": 5042, 
    "source": "Novel", 
    "episodes": "13", 
    "year": 2015, 
    "duration": 23, 
    "type": "", 
    "id": 27741
}