{
    "rating": "PG", 
    "studios": [
        "Shin-Ei Animation"
    ], 
    "licensors": [], 
    "title": "Ninja Hattori-kun Plus Perman: Chounouryoku Wars", 
    "url": "/anime/29235/Ninja_Hattori-kun_Plus_Perman__Chounouryoku_Wars", 
    "popularity": 11698, 
    "public_score": 6.17, 
    "genres": [
        "Adventure", 
        "Martial Arts", 
        "Super Power"
    ], 
    "rank": 6910, 
    "source": "Unknown", 
    "episodes": "1", 
    "year": 1984, 
    "duration": 55, 
    "type": "", 
    "id": 29235
}