{
    "rating": "R+", 
    "studios": [
        "AIC"
    ], 
    "licensors": [
        "Funimation"
    ], 
    "title": "Maken-Ki!", 
    "url": "/anime/9936/Maken-Ki", 
    "popularity": 584, 
    "public_score": 6.61, 
    "genres": [
        "Action", 
        "Ecchi", 
        "Harem", 
        "Martial Arts", 
        "School", 
        "Super Power"
    ], 
    "rank": 5171, 
    "source": "Manga", 
    "episodes": "12", 
    "year": 2011, 
    "duration": 25, 
    "type": "", 
    "id": 9936
}