{
    "rating": "PG-13", 
    "studios": [
        "Telecom Animation Film"
    ], 
    "licensors": [
        "Bandai Entertainment"
    ], 
    "title": "Tide-Line Blue: Kyoudai", 
    "url": "/anime/1001/Tide-Line_Blue__Kyoudai", 
    "popularity": 7671, 
    "public_score": 6.76, 
    "genres": [
        "Adventure", 
        "Drama", 
        "Shounen"
    ], 
    "rank": 4517, 
    "source": "Original", 
    "episodes": 1, 
    "year": 2006, 
    "duration": 23, 
    "type": "Special", 
    "id": 1001
}