{
    "rating": "PG-13", 
    "studios": [
        "Bones"
    ], 
    "licensors": [
        "Sentai Filmworks"
    ], 
    "title": "Towa no Quon 3: Mugen no Renza", 
    "url": "/anime/10714/Towa_no_Quon_3__Mugen_no_Renza", 
    "popularity": 2459, 
    "public_score": 7.59, 
    "genres": [
        "Action", 
        "Sci-Fi", 
        "Super Power", 
        "Psychological", 
        "Supernatural"
    ], 
    "rank": 1396, 
    "source": "Original", 
    "episodes": "1", 
    "year": 2011, 
    "duration": 48, 
    "type": "Movie", 
    "id": 10714
}