{
    "rating": "PG-13", 
    "studios": [
        "Gonzo"
    ], 
    "licensors": [
        "Funimation"
    ], 
    "title": "Giniro no Kami no Agito", 
    "url": "/anime/1140/Giniro_no_Kami_no_Agito", 
    "popularity": 1500, 
    "public_score": 7.22, 
    "genres": [
        "Adventure", 
        "Drama", 
        "Fantasy", 
        "Romance", 
        "Sci-Fi"
    ], 
    "rank": 2729, 
    "source": "Original", 
    "episodes": "1", 
    "year": 2006, 
    "duration": 135, 
    "type": "Movie", 
    "id": 1140
}