{
    "rating": "R+", 
    "studios": [
        "Studio Deen"
    ], 
    "licensors": [
        "Funimation"
    ], 
    "title": "Sankarea", 
    "url": "/anime/11499/Sankarea", 
    "popularity": 205, 
    "public_score": 7.48, 
    "genres": [
        "Comedy", 
        "Horror", 
        "Supernatural", 
        "Romance", 
        "Ecchi", 
        "Shounen"
    ], 
    "rank": 1704, 
    "source": "Manga", 
    "episodes": 12, 
    "year": 2012, 
    "duration": 24, 
    "type": "TV", 
    "id": 11499
}