{
    "rating": "G", 
    "studios": [
        "TYO Animations"
    ], 
    "licensors": null, 
    "title": "Tamayura: Hitotose - Attakai Kaze no Omoide, Nanode", 
    "url": "/anime/11793/Tamayura__Hitotose_-_Attakai_Kaze_no_Omoide_Nanode", 
    "popularity": 4520, 
    "public_score": 7.43, 
    "genres": [
        "Comedy", 
        "Drama", 
        "Slice of Life"
    ], 
    "rank": 1905, 
    "source": "Original", 
    "episodes": "1", 
    "year": 2012, 
    "duration": 24, 
    "type": "Special", 
    "id": 11793
}