{
    "rating": "PG-13", 
    "studios": [
        "J.C.Staff"
    ], 
    "licensors": [
        "Media Blasters"
    ], 
    "title": "Loveless", 
    "url": "/anime/149/Loveless", 
    "popularity": 902, 
    "public_score": 7.09, 
    "genres": [
        "Action", 
        "Mystery", 
        "Supernatural", 
        "Drama", 
        "Romance", 
        "Fantasy", 
        "Josei", 
        "Shounen Ai"
    ], 
    "rank": 3248, 
    "source": "Manga", 
    "episodes": 12, 
    "year": 2005, 
    "duration": 24, 
    "type": "TV", 
    "id": 149
}