{
    "rating": "PG-13", 
    "studios": [
        "Hoods Entertainment", 
        "Production IMS"
    ], 
    "licensors": [
        "Sentai Filmworks"
    ], 
    "title": "Fantasista Doll", 
    "url": "/anime/15883/Fantasista_Doll", 
    "popularity": 2661, 
    "public_score": 6.22, 
    "genres": [
        "Sci-Fi", 
        "Magic", 
        "Fantasy"
    ], 
    "rank": 6704, 
    "source": "Original", 
    "episodes": "12", 
    "year": 2013, 
    "duration": 23, 
    "type": "TV", 
    "id": 15883
}