{
    "rating": "PG-13", 
    "studios": [
        "Studio Hibari"
    ], 
    "licensors": [
        "ADV Films", 
        "Funimation"
    ], 
    "title": "Venus Versus Virus", 
    "url": "/anime/1607/Venus_Versus_Virus", 
    "popularity": 2515, 
    "public_score": 6.48, 
    "genres": [
        "Drama", 
        "Romance", 
        "Supernatural"
    ], 
    "rank": 5715, 
    "source": "Manga", 
    "episodes": "12", 
    "year": 2007, 
    "duration": 24, 
    "type": "TV", 
    "id": 1607
}