{
    "rating": "R+", 
    "studios": [
        "Barnum Studio", 
        "Project No.9"
    ], 
    "licensors": [
        "Active"
    ], 
    "title": "Zettai Junpaku\u2661Mahou Shoujo", 
    "url": "/anime/16656/Zettai_Junpaku\u2661Mahou_Shoujo", 
    "popularity": 4132, 
    "public_score": 5.39, 
    "genres": [
        "Action", 
        "Ecchi", 
        "Harem", 
        "Magic"
    ], 
    "rank": 8761, 
    "source": "Manga", 
    "episodes": "1", 
    "year": 2012, 
    "duration": 6, 
    "type": "", 
    "id": 16656
}