{
    "rating": "PG-13", 
    "studios": [
        "Studio Gokumi"
    ], 
    "licensors": [
        "Sentai Filmworks"
    ], 
    "title": "Kiniro Mosaic", 
    "url": "/anime/16732/Kiniro_Mosaic", 
    "popularity": 810, 
    "public_score": 7.35, 
    "genres": [
        "Slice of Life", 
        "Comedy", 
        "School", 
        "Seinen"
    ], 
    "rank": 2232, 
    "source": "4-koma manga", 
    "episodes": 12, 
    "year": 2013, 
    "duration": 24, 
    "type": "TV", 
    "id": 16732
}