{
    "rating": "G", 
    "studios": [
        "Nippon Animation"
    ], 
    "licensors": null, 
    "title": "Les Mis\u00e9rables: Shoujo Cosette", 
    "url": "/anime/1695/Les_Mis\u00e9rables__Shoujo_Cosette", 
    "popularity": 3325, 
    "public_score": 7.97, 
    "genres": [
        "Slice of Life", 
        "Historical", 
        "Drama", 
        "Shoujo"
    ], 
    "rank": 591, 
    "source": "Novel", 
    "episodes": 52, 
    "year": 2007, 
    "duration": 24, 
    "type": "TV", 
    "id": 1695
}