{
    "rating": "R+", 
    "studios": null, 
    "licensors": [
        "Urban Vision"
    ], 
    "title": "Golgo 13: Queen Bee", 
    "url": "/anime/1761/Golgo_13__Queen_Bee", 
    "popularity": 4686, 
    "public_score": 6.67, 
    "genres": [
        "Action", 
        "Adventure", 
        "Military", 
        "Drama", 
        "Seinen"
    ], 
    "rank": 4897, 
    "source": "Manga", 
    "episodes": 1, 
    "year": 1998, 
    "duration": 56, 
    "type": "OVA", 
    "id": 1761
}