{
    "rating": "PG-13", 
    "studios": [
        "J.C.Staff"
    ], 
    "licensors": null, 
    "title": "Yomigaeru Sora: Rescue Wings - Saigo no Shigoto", 
    "url": "/anime/1843/Yomigaeru_Sora__Rescue_Wings_-_Saigo_no_Shigoto", 
    "popularity": 6848, 
    "public_score": 7.04, 
    "genres": [
        "Military", 
        "Drama", 
        "Seinen"
    ], 
    "rank": 3450, 
    "source": "Original", 
    "episodes": 1, 
    "year": 2006, 
    "duration": 22, 
    "type": "Special", 
    "id": 1843
}