{
    "rating": "PG-13", 
    "studios": null, 
    "licensors": null, 
    "title": "Harukanaru Toki no Naka de 2: Shiroki Ryuu no Miko", 
    "url": "/anime/1904/Harukanaru_Toki_no_Naka_de_2__Shiroki_Ryuu_no_Miko", 
    "popularity": 6624, 
    "public_score": 6.69, 
    "genres": [
        "Fantasy", 
        "Magic", 
        "Romance", 
        "Supernatural", 
        "Demons", 
        "Historical", 
        "Shoujo"
    ], 
    "rank": 4813, 
    "source": "Visual novel", 
    "episodes": "3", 
    "year": 2003, 
    "duration": 30, 
    "type": "OVA", 
    "id": 1904
}