{
    "rating": "PG-13", 
    "studios": [
        "Production I.G"
    ], 
    "licensors": null, 
    "title": "Wellber no Monogatari: Sisters of Wellber", 
    "url": "/anime/2032/Wellber_no_Monogatari__Sisters_of_Wellber", 
    "popularity": 4492, 
    "public_score": 6.74, 
    "genres": [
        "Action", 
        "Adventure", 
        "Comedy", 
        "Drama", 
        "Fantasy", 
        "Historical"
    ], 
    "rank": 4609, 
    "source": "Original", 
    "episodes": "13", 
    "year": 2007, 
    "duration": 24, 
    "type": "TV", 
    "id": 2032
}