{
    "rating": "PG-13", 
    "studios": [
        "Studio Pierrot"
    ], 
    "licensors": null, 
    "title": "Majokko Club Yoningumi: A Kuukan kara no Alien X", 
    "url": "/anime/2080/Majokko_Club_Yoningumi__A_Kuukan_kara_no_Alien_X", 
    "popularity": 9430, 
    "public_score": 5.79, 
    "genres": [
        "Action", 
        "Parody", 
        "Magic", 
        "Comedy", 
        "Sci-Fi"
    ], 
    "rank": 7949, 
    "source": "Original", 
    "episodes": "1", 
    "year": 1987, 
    "duration": 27, 
    "type": "OVA", 
    "id": 2080
}