{
    "rating": "R+", 
    "studios": [
        "Studio Fantasia"
    ], 
    "licensors": [
        "Bandai Entertainment"
    ], 
    "title": "AIKa R-16: Virgin Mission", 
    "url": "/anime/2163/AIKa_R-16__Virgin_Mission", 
    "popularity": 3078, 
    "public_score": 6.05, 
    "genres": [
        "Action", 
        "Ecchi", 
        "Comedy"
    ], 
    "rank": 7287, 
    "source": null, 
    "episodes": 3, 
    "year": 2007, 
    "duration": 25, 
    "type": "OVA", 
    "id": 2163
}