{
    "rating": "PG", 
    "studios": null, 
    "licensors": null, 
    "title": "Sore Ike! Anpanman: Anpanman to Yukai na Nakama-tachi", 
    "url": "/anime/21937/Sore_Ike_Anpanman__Anpanman_to_Yukai_na_Nakama-tachi", 
    "popularity": 12217, 
    "public_score": 5.29, 
    "genres": [
        "Comedy", 
        "Fantasy", 
        "Kids"
    ], 
    "rank": 12447, 
    "source": null, 
    "episodes": 1, 
    "year": 1992, 
    "duration": 31, 
    "type": "Movie", 
    "id": 21937
}