{
    "rating": "Rx", 
    "studios": null, 
    "licensors": null, 
    "title": "Pandra The Animation: Shiroki Yokubou Kuro no Kibou", 
    "url": "/anime/22347/Pandra_The_Animation__Shiroki_Yokubou_Kuro_no_Kibou", 
    "popularity": 5261, 
    "public_score": 7.02, 
    "genres": [
        "Fantasy", 
        "Hentai", 
        "Supernatural", 
        "Demons"
    ], 
    "rank": null, 
    "source": "Manga", 
    "episodes": 2, 
    "year": 2014, 
    "duration": 27, 
    "type": "OVA", 
    "id": 22347
}