{
    "rating": "R", 
    "studios": [
        "Sunrise"
    ], 
    "licensors": [
        "Bandai Entertainment"
    ], 
    "title": "Mobile Suit Gundam SEED Special Edition", 
    "url": "/anime/2269/Mobile_Suit_Gundam_SEED_Special_Edition", 
    "popularity": 4138, 
    "public_score": 7.42, 
    "genres": [
        "Action", 
        "Space", 
        "Mecha", 
        "Military", 
        "Sci-Fi"
    ], 
    "rank": 1933, 
    "source": "Original", 
    "episodes": "3", 
    "year": 2004, 
    "duration": 135, 
    "type": "Special", 
    "id": 2269
}