{
    "rating": "PG-13", 
    "studios": [
        "Studio 3Hz"
    ], 
    "licensors": [
        "Sentai Filmworks"
    ], 
    "title": "Sora no Method", 
    "url": "/anime/23209/Sora_no_Method", 
    "popularity": 1321, 
    "public_score": 6.79, 
    "genres": [
        "Slice of Life", 
        "Drama", 
        "Fantasy", 
        "School"
    ], 
    "rank": 4381, 
    "source": "Original", 
    "episodes": "13", 
    "year": 2014, 
    "duration": 24, 
    "type": "TV", 
    "id": 23209
}