{
    "rating": "PG", 
    "studios": [
        "Shin-Ei Animation"
    ], 
    "licensors": null, 
    "title": "Doraemon Movie 35: Nobita no Space Heroes", 
    "url": "/anime/25383/Doraemon_Movie_35__Nobita_no_Space_Heroes", 
    "popularity": 8620, 
    "public_score": 6.95, 
    "genres": [
        "Comedy", 
        "Kids", 
        "Shounen", 
        "Space"
    ], 
    "rank": 3712, 
    "source": null, 
    "episodes": "1", 
    "year": 2015, 
    "duration": 140, 
    "type": "Movie", 
    "id": 25383
}