{
    "rating": "PG-13", 
    "studios": [
        "J.C.Staff"
    ], 
    "licensors": [
        "Sentai Filmworks"
    ], 
    "title": "Dungeon ni Deai wo Motomeru no wa Machigatteiru Darou ka", 
    "url": "/anime/28121/Dungeon_ni_Deai_wo_Motomeru_no_wa_Machigatteiru_Darou_ka", 
    "popularity": 60, 
    "public_score": 7.82, 
    "genres": [
        "Action", 
        "Adventure", 
        "Comedy", 
        "Romance", 
        "Fantasy"
    ], 
    "rank": 845, 
    "source": "Light novel", 
    "episodes": "13", 
    "year": 2015, 
    "duration": 24, 
    "type": "TV", 
    "id": 28121
}