{
    "rating": "PG-13", 
    "studios": [
        "Sunrise"
    ], 
    "licensors": null, 
    "title": "Gundam: G no Reconguista - From the Past to the Future", 
    "url": "/anime/31454/Gundam__G_no_Reconguista_-_From_the_Past_to_the_Future", 
    "popularity": 7975, 
    "public_score": 6.12, 
    "genres": [
        "Action", 
        "Mecha", 
        "Sci-Fi", 
        "Space"
    ], 
    "rank": 7082, 
    "source": "Original", 
    "episodes": "1", 
    "year": 2015, 
    "duration": 9, 
    "type": "Special", 
    "id": 31454
}