{
    "rating": "PG-13", 
    "studios": [
        "Kinema Citrus"
    ], 
    "licensors": [
        "Sentai Filmworks"
    ], 
    "title": "Norn9: Norn+Nonet", 
    "url": "/anime/31452/Norn9__Norn_Nonet", 
    "popularity": 1534, 
    "public_score": 6.68, 
    "genres": [
        "Sci-Fi", 
        "Adventure", 
        "Romance", 
        "Fantasy", 
        "Josei"
    ], 
    "rank": 4864, 
    "source": "Visual novel", 
    "episodes": 12, 
    "year": 2016, 
    "duration": 24, 
    "type": "TV", 
    "id": 31452
}