{
    "rating": "PG-13", 
    "studios": [
        "Creators in Pack"
    ], 
    "licensors": null, 
    "title": "Danchigai: Juusan Goutou Sentou Ikitai!!", 
    "url": "/anime/31683/Danchigai__Juusan_Goutou_Sentou_Ikitai", 
    "popularity": 3496, 
    "public_score": 6.48, 
    "genres": [
        "Slice of Life", 
        "Comedy"
    ], 
    "rank": 5687, 
    "source": "4-koma manga", 
    "episodes": 1, 
    "year": 2015, 
    "duration": 3, 
    "type": "Special", 
    "id": 31683
}