{
    "rating": "PG", 
    "studios": [
        "OLM"
    ], 
    "licensors": [], 
    "title": "TV-ban Pokemon Special Masara Town-hen Recaps", 
    "url": "/anime/31750/TV-ban_Pokemon_Special_Masara_Town-hen_Recaps", 
    "popularity": 8179, 
    "public_score": 6.18, 
    "genres": [
        "Action", 
        "Adventure", 
        "Comedy", 
        "Kids", 
        "Fantasy"
    ], 
    "rank": 6875, 
    "source": "Game", 
    "episodes": "3", 
    "year": 2000, 
    "duration": 47, 
    "type": "", 
    "id": 31750
}