{
    "rating": "G", 
    "studios": [
        "OLM"
    ], 
    "licensors": [], 
    "title": "Youkai Watch Movie 3: Soratobu Kujira to Double Sekai no Daibouken da Nyan!", 
    "url": "/anime/32222/Youkai_Watch_Movie_3__Soratobu_Kujira_to_Double_Sekai_no_Daibouken_da_Nyan", 
    "popularity": 9505, 
    "public_score": 6.59, 
    "genres": [
        "Comedy", 
        "Kids", 
        "Supernatural"
    ], 
    "rank": 5280, 
    "source": "Game", 
    "episodes": "1", 
    "year": 2016, 
    "duration": 130, 
    "type": "", 
    "id": 32222
}