{
    "rating": "R", 
    "studios": [
        "Bones"
    ], 
    "licensors": [
        "Funimation", 
        "Crunchyroll"
    ], 
    "title": "Bungou Stray Dogs 2nd Season", 
    "url": "/anime/32867/Bungou_Stray_Dogs_2nd_Season", 
    "popularity": 361, 
    "public_score": 8.31, 
    "genres": [
        "Action", 
        "Mystery", 
        "Seinen", 
        "Super Power", 
        "Supernatural"
    ], 
    "rank": 231, 
    "source": "Manga", 
    "episodes": 12, 
    "year": 2016, 
    "duration": 23, 
    "type": "TV", 
    "id": 32867
}