{
    "rating": "PG-13", 
    "studios": [
        "Bandai Namco Pictures"
    ], 
    "licensors": null, 
    "title": "Gintama.", 
    "url": "/anime/34096/Gintama", 
    "popularity": 908, 
    "public_score": 9.01, 
    "genres": [
        "Action", 
        "Comedy", 
        "Historical", 
        "Parody", 
        "Samurai", 
        "Sci-Fi", 
        "Shounen"
    ], 
    "rank": 12, 
    "source": "Manga", 
    "episodes": 12, 
    "year": 2017, 
    "duration": 24, 
    "type": "TV", 
    "id": 34096
}