{
    "rating": "PG-13", 
    "studios": [
        "Shaft"
    ], 
    "licensors": [
        "Funimation"
    ], 
    "title": "Tsukuyomi: Moon Phase", 
    "url": "/anime/343/Tsukuyomi__Moon_Phase", 
    "popularity": 1502, 
    "public_score": 7.1, 
    "genres": [
        "Comedy", 
        "Romance", 
        "Vampire", 
        "Fantasy", 
        "Seinen"
    ], 
    "rank": 3233, 
    "source": "Manga", 
    "episodes": 25, 
    "year": 2004, 
    "duration": 24, 
    "type": "TV", 
    "id": 343
}