{
    "rating": "Rx", 
    "studios": [
        "Collaboration Works"
    ], 
    "licensors": null, 
    "title": "Nuki Doki! Tenshi to Akuma no Sakusei Battle - Revolution", 
    "url": "/anime/34492/Nuki_Doki_Tenshi_to_Akuma_no_Sakusei_Battle_-_Revolution", 
    "popularity": 5401, 
    "public_score": 6.36, 
    "genres": [
        "Hentai"
    ], 
    "rank": null, 
    "source": "Visual novel", 
    "episodes": "4", 
    "year": 2017, 
    "duration": 17, 
    "type": "OVA", 
    "id": 34492
}