{
    "rating": "G", 
    "studios": [
        "Studio Deen"
    ], 
    "licensors": null, 
    "title": "Washimo 5th Season", 
    "url": "/anime/35295/Washimo_5th_Season", 
    "popularity": 13308, 
    "public_score": 4.14, 
    "genres": [
        "Sci-Fi", 
        "Slice of Life", 
        "Comedy", 
        "Kids", 
        "School"
    ], 
    "rank": 12901, 
    "source": "Picture book", 
    "episodes": "44", 
    "year": 2017, 
    "duration": 10, 
    "type": "TV", 
    "id": 35295
}