{
    "rating": "PG-13", 
    "studios": [
        "Studio Gallop"
    ], 
    "licensors": null, 
    "title": "Kochira Katsushikaku Kameari Kouenmae Hashutsujo (TV)", 
    "url": "/anime/3545/Kochira_Katsushikaku_Kameari_Kouenmae_Hashutsujo_TV", 
    "popularity": 4355, 
    "public_score": 7.78, 
    "genres": [
        "Slice of Life", 
        "Comedy", 
        "Police"
    ], 
    "rank": 922, 
    "source": "Manga", 
    "episodes": "373", 
    "year": 1996, 
    "duration": 25, 
    "type": "TV", 
    "id": 3545
}