{
    "rating": "Rx", 
    "studios": null, 
    "licensors": null, 
    "title": "Pakomane: Watashi, Kyou kara Meimon Yakyuubu no Seishorigakari ni Narimasu... The Animation", 
    "url": "/anime/36461/Pakomane__Watashi_Kyou_kara_Meimon_Yakyuubu_no_Seishorigakari_ni_Narimasu_The_Animation", 
    "popularity": 7194, 
    "public_score": 6.6, 
    "genres": [
        "Hentai"
    ], 
    "rank": null, 
    "source": "Visual novel", 
    "episodes": 1, 
    "year": 2017, 
    "duration": 28, 
    "type": "OVA", 
    "id": 36461
}