{
    "rating": "PG", 
    "studios": [
        "OLM"
    ], 
    "licensors": null, 
    "title": "Shinkansen Henkei Robo Shinkalion The Animation", 
    "url": "/anime/36531/Shinkansen_Henkei_Robo_Shinkalion_The_Animation", 
    "popularity": 7745, 
    "public_score": 6.06, 
    "genres": [
        "Action", 
        "Sci-Fi", 
        "Kids", 
        "Mecha"
    ], 
    "rank": 7281, 
    "source": "Other", 
    "episodes": null, 
    "year": 2018, 
    "duration": 24, 
    "type": "TV", 
    "id": 36531
}