{
    "rating": "PG-13", 
    "studios": [
        "Haoliners Animation League"
    ], 
    "licensors": null, 
    "title": "Huyao Xiao Hongniang: Beishan Yaodi", 
    "url": "/anime/36823/Huyao_Xiao_Hongniang__Beishan_Yaodi", 
    "popularity": 5904, 
    "public_score": 7.64, 
    "genres": [
        "Comedy", 
        "Historical", 
        "Supernatural", 
        "Romance"
    ], 
    "rank": 1243, 
    "source": "Manga", 
    "episodes": "8", 
    "year": 2016, 
    "duration": 14, 
    "type": "ONA", 
    "id": 36823
}