{
    "rating": "R", 
    "studios": null, 
    "licensors": null, 
    "title": "Psycho-Pass SS Case 1: Tsumi to Batsu", 
    "url": "/anime/37440/Psycho-Pass_SS_Case_1__Tsumi_to_Batsu", 
    "popularity": 2924, 
    "public_score": null, 
    "genres": [
        "Action", 
        "Police", 
        "Psychological", 
        "Sci-Fi"
    ], 
    "rank": null, 
    "source": "Original", 
    "episodes": 1, 
    "year": 2019, 
    "duration": null, 
    "type": "Movie", 
    "id": 37440
}