{
    "rating": "None", 
    "studios": null, 
    "licensors": null, 
    "title": "Psycho-Pass SS Case 2: First Guardian", 
    "url": "/anime/37441/Psycho-Pass_SS_Case_2__First_Guardian", 
    "popularity": 4582, 
    "public_score": null, 
    "genres": [
        "Action", 
        "Police", 
        "Psychological", 
        "Sci-Fi"
    ], 
    "rank": null, 
    "source": "Original", 
    "episodes": 1, 
    "year": null, 
    "duration": null, 
    "type": "Movie", 
    "id": 37441
}