{
    "rating": "G", 
    "studios": [
        "Tatsunoko Production"
    ], 
    "licensors": [
        "Saban Entertainment"
    ], 
    "title": "Mori no Youki na Kobito-tachi: Belfy to Lillibit", 
    "url": "/anime/3810/Mori_no_Youki_na_Kobito-tachi__Belfy_to_Lillibit", 
    "popularity": 8960, 
    "public_score": 6.51, 
    "genres": [
        "Adventure", 
        "Fantasy", 
        "Comedy"
    ], 
    "rank": 5583, 
    "source": null, 
    "episodes": "26", 
    "year": 1980, 
    "duration": 25, 
    "type": "TV", 
    "id": 3810
}