{
    "rating": "PG-13", 
    "studios": [
        "Nippon Animation"
    ], 
    "licensors": null, 
    "title": "Shiritsu Araiso Koutougakkou Seitokai Shikkoubu", 
    "url": "/anime/425/Shiritsu_Araiso_Koutougakkou_Seitokai_Shikkoubu", 
    "popularity": 5091, 
    "public_score": 6.54, 
    "genres": [
        "Comedy", 
        "Sports", 
        "Shounen Ai"
    ], 
    "rank": 5479, 
    "source": "Manga", 
    "episodes": "2", 
    "year": 2002, 
    "duration": 26, 
    "type": "OVA", 
    "id": 425
}