{
    "rating": "PG-13", 
    "studios": [
        "Shaft"
    ], 
    "licensors": [
        "Sentai Filmworks"
    ], 
    "title": "Maria\u2020Holic", 
    "url": "/anime/5030/Maria\u2020Holic", 
    "popularity": 740, 
    "public_score": 7.13, 
    "genres": [
        "Comedy", 
        "Parody", 
        "School", 
        "Shoujo Ai"
    ], 
    "rank": 3091, 
    "source": "Manga", 
    "episodes": 12, 
    "year": 2009, 
    "duration": 24, 
    "type": "TV", 
    "id": 5030
}