{
    "rating": "PG-13", 
    "studios": [
        "Toei Animation"
    ], 
    "licensors": null, 
    "title": "One Piece: Romance Dawn Story", 
    "url": "/anime/5252/One_Piece__Romance_Dawn_Story", 
    "popularity": 2312, 
    "public_score": 7.49, 
    "genres": [
        "Action", 
        "Fantasy", 
        "Comedy", 
        "Super Power", 
        "Shounen"
    ], 
    "rank": 1674, 
    "source": "Manga", 
    "episodes": 1, 
    "year": 2008, 
    "duration": 33, 
    "type": "OVA", 
    "id": 5252
}