{
    "rating": "PG-13", 
    "studios": [
        "Xebec"
    ], 
    "licensors": [
        "Funimation", 
        "Geneon Entertainment USA"
    ], 
    "title": "Soukyuu no Fafner: Dead Aggressor", 
    "url": "/anime/75/Soukyuu_no_Fafner__Dead_Aggressor", 
    "popularity": 2059, 
    "public_score": 7.36, 
    "genres": [
        "Action", 
        "Drama", 
        "Mecha", 
        "Military", 
        "Sci-Fi"
    ], 
    "rank": 2198, 
    "source": "Original", 
    "episodes": "25", 
    "year": 2004, 
    "duration": 24, 
    "type": "TV", 
    "id": 75
}