{
    "rating": "PG-13", 
    "studios": [
        "Triangle Staff"
    ], 
    "licensors": [
        "Discotek Media", 
        "Geneon Entertainment USA"
    ], 
    "title": "NieA Under 7", 
    "url": "/anime/800/NieA_Under_7", 
    "popularity": 2630, 
    "public_score": 6.92, 
    "genres": [
        "Comedy", 
        "Sci-Fi", 
        "Slice of Life"
    ], 
    "rank": 3873, 
    "source": "Original", 
    "episodes": "13", 
    "year": 2000, 
    "duration": 23, 
    "type": "TV", 
    "id": 800
}