{
    "rating": "G", 
    "studios": [
        "Toei Animation"
    ], 
    "licensors": null, 
    "title": "Gegege no Kitarou: Youkai Tokkyuu! Maboroshi no Kisha", 
    "url": "/anime/8157/Gegege_no_Kitarou__Youkai_Tokkyuu_Maboroshi_no_Kisha", 
    "popularity": 10086, 
    "public_score": 6.24, 
    "genres": [
        "Adventure", 
        "Comedy", 
        "Fantasy", 
        "Horror", 
        "Supernatural"
    ], 
    "rank": 6640, 
    "source": null, 
    "episodes": "1", 
    "year": 1997, 
    "duration": 23, 
    "type": "Movie", 
    "id": 8157
}