{
    "rating": "PG-13", 
    "studios": [
        "Studio Deen"
    ], 
    "licensors": null, 
    "title": "Vampire Knight: Gekiai no Portrait", 
    "url": "/anime/8422/Vampire_Knight__Gekiai_no_Portrait", 
    "popularity": 2271, 
    "public_score": 6.99, 
    "genres": [
        "Comedy", 
        "Vampire", 
        "Shoujo"
    ], 
    "rank": 3630, 
    "source": "Manga", 
    "episodes": 1, 
    "year": 2008, 
    "duration": 3, 
    "type": "Special", 
    "id": 8422
}