{
    "rating": "PG", 
    "studios": [
        "OLM"
    ], 
    "licensors": [
        "The Pokemon Company International"
    ], 
    "title": "Pokemon Ranger: Hikari no Kiseki", 
    "url": "/anime/8438/Pokemon_Ranger__Hikari_no_Kiseki", 
    "popularity": 4620, 
    "public_score": 6.59, 
    "genres": [
        "Adventure", 
        "Comedy", 
        "Fantasy", 
        "Kids"
    ], 
    "rank": 5271, 
    "source": "Game", 
    "episodes": "2", 
    "year": 2010, 
    "duration": 5, 
    "type": "Special", 
    "id": 8438
}