{
    "rating": "PG-13", 
    "studios": [
        "Bee Train"
    ], 
    "licensors": [
        "Funimation", 
        "Bandai Entertainment"
    ], 
    "title": ".hack//Roots", 
    "url": "/anime/873/hack__Roots", 
    "popularity": 1433, 
    "public_score": 7.01, 
    "genres": [
        "Adventure", 
        "Drama", 
        "Fantasy", 
        "Game", 
        "Sci-Fi"
    ], 
    "rank": 3537, 
    "source": "Original", 
    "episodes": 26, 
    "year": 2006, 
    "duration": 24, 
    "type": "TV", 
    "id": 873
}