{
    "rating": "PG", 
    "studios": [
        "Toei Animation"
    ], 
    "licensors": null, 
    "title": "Transformers Headmasters", 
    "url": "/anime/925/Transformers_Headmasters", 
    "popularity": 6817, 
    "public_score": 6.61, 
    "genres": [
        "Adventure", 
        "Mecha", 
        "Sci-Fi", 
        "Shounen"
    ], 
    "rank": 5195, 
    "source": null, 
    "episodes": 35, 
    "year": 1987, 
    "duration": 23, 
    "type": "TV", 
    "id": 925
}