{
    "rating": "Rx", 
    "studios": [
        "Office Take Off"
    ], 
    "licensors": null, 
    "title": "Ane Jiru 2 The Animation: Shirakawa Sanshimai ni Omakase", 
    "url": "/anime/9435/Ane_Jiru_2_The_Animation__Shirakawa_Sanshimai_ni_Omakase", 
    "popularity": 4043, 
    "public_score": 7.09, 
    "genres": [
        "Hentai"
    ], 
    "rank": null, 
    "source": "Visual novel", 
    "episodes": 2, 
    "year": 2010, 
    "duration": 28, 
    "type": "OVA", 
    "id": 9435
}